verilog/synchronizer/sync0.v
`timescale 1ns/100ps
module sync(
		input	d_i,
		input	clk_i,
		input	rst_i,
		output	q_o
);
reg	r0;
reg	r1;
reg	r2;
localparam DELAY=1;
always@(posedge clk_i or posedge rst_i) begin
	if(rst_i) begin
		r0 <= # DELAY 1'b0;
		r1 <= # DELAY 1'b0;
		r2 <= # DELAY 1'b0;
	end else begin
		r0 <= # DELAY d_i;
		r1 <= # DELAY r0;
		r2 <= # DELAY r1;
	end
end

assign q_o = r2;

endmodule

verilog/synchronizer/sync_tb.v
`timescale 1ns/100ps
module	sync_tb;
	reg		d;
	reg		clk;
	reg		rst;
	wire	q;
integer i=0;
initial begin
	clk = 1'b0;
	rst = 1'b1;
	#50	rst = 1'b0;


	for (i=0;i!=1000;i=i+1) begin
		//$display("dbg");
		#5 clk <=  ~clk;
	end

end


	sync u0(
			.d_i(d),
			.clk_i(clk),
			.rst_i(rst),
			.q_o(q)
	);

initial begin
	d = 1'b0;
	$dumpfile("sync_wv.vcd");
	$dumpvars(0,sync_tb);
	#100 d = 1'b1;
	#10 d =1'b0;
	#10 d =1'b1;

	# 500;
	$finish;
end

endmodule

verilog/synchronizer/sync_wv.vcd
$date
	Tue Feb 15 23:30:52 2022
$end
$version
	Icarus Verilog
$end
$timescale
	100ps
$end
$scope module sync_tb $end
$var wire 1 ! q $end
$var reg 1 " clk $end
$var reg 1 # d $end
$var reg 1 $ rst $end
$var integer 32 % i [31:0] $end
$scope module u0 $end
$var wire 1 " clk_i $end
$var wire 1 # d_i $end
$var wire 1 ! q_o $end
$var wire 1 $ rst_i $end
$var reg 1 & r0 $end
$var reg 1 ' r1 $end
$var reg 1 ( r2 $end
$upscope $end
$upscope $end
$enddefinitions $end
#0
$dumpvars
x(
x'
x&
b0 %
1$
0#
0"
x!
$end
#10
0!
0(
0'
0&
#500
0$
#550
1"
b1 %
#600
0"
b10 %
#650
1"
b11 %
#700
0"
b100 %
#750
1"
b101 %
#800
0"
b110 %
#850
1"
b111 %
#900
0"
b1000 %
#950
1"
b1001 %
#1000
0"
b1010 %
1#
#1050
1"
b1011 %
#1060
1&
#1100
0"
b1100 %
0#
#1150
1"
b1101 %
#1160
1'
0&
#1200
0"
b1110 %
1#
#1250
1"
b1111 %
#1260
1!
1(
0'
1&
#1300
0"
b10000 %
#1350
1"
b10001 %
#1360
0!
0(
1'
#1400
0"
b10010 %
#1450
1"
b10011 %
#1460
1!
1(
#1500
0"
b10100 %
#1550
1"
b10101 %
#1600
0"
b10110 %
#1650
1"
b10111 %
#1700
0"
b11000 %
#1750
1"
b11001 %
#1800
0"
b11010 %
#1850
1"
b11011 %
#1900
0"
b11100 %
#1950
1"
b11101 %
#2000
0"
b11110 %
#2050
1"
b11111 %
#2100
0"
b100000 %
#2150
1"
b100001 %
#2200
0"
b100010 %
#2250
1"
b100011 %
#2300
0"
b100100 %
#2350
1"
b100101 %
#2400
0"
b100110 %
#2450
1"
b100111 %
#2500
0"
b101000 %
#2550
1"
b101001 %
#2600
0"
b101010 %
#2650
1"
b101011 %
#2700
0"
b101100 %
#2750
1"
b101101 %
#2800
0"
b101110 %
#2850
1"
b101111 %
#2900
0"
b110000 %
#2950
1"
b110001 %
#3000
0"
b110010 %
#3050
1"
b110011 %
#3100
0"
b110100 %
#3150
1"
b110101 %
#3200
0"
b110110 %
#3250
1"
b110111 %
#3300
0"
b111000 %
#3350
1"
b111001 %
#3400
0"
b111010 %
#3450
1"
b111011 %
#3500
0"
b111100 %
#3550
1"
b111101 %
#3600
0"
b111110 %
#3650
1"
b111111 %
#3700
0"
b1000000 %
#3750
1"
b1000001 %
#3800
0"
b1000010 %
#3850
1"
b1000011 %
#3900
0"
b1000100 %
#3950
1"
b1000101 %
#4000
0"
b1000110 %
#4050
1"
b1000111 %
#4100
0"
b1001000 %
#4150
1"
b1001001 %
#4200
0"
b1001010 %
#4250
1"
b1001011 %
#4300
0"
b1001100 %
#4350
1"
b1001101 %
#4400
0"
b1001110 %
#4450
1"
b1001111 %
#4500
0"
b1010000 %
#4550
1"
b1010001 %
#4600
0"
b1010010 %
#4650
1"
b1010011 %
#4700
0"
b1010100 %
#4750
1"
b1010101 %
#4800
0"
b1010110 %
#4850
1"
b1010111 %
#4900
0"
b1011000 %
#4950
1"
b1011001 %
#5000
0"
b1011010 %
#5050
1"
b1011011 %
#5100
0"
b1011100 %
#5150
1"
b1011101 %
#5200
0"
b1011110 %
#5250
1"
b1011111 %
#5300
0"
b1100000 %
#5350
1"
b1100001 %
#5400
0"
b1100010 %
#5450
1"
b1100011 %
#5500
0"
b1100100 %
#5550
1"
b1100101 %
#5600
0"
b1100110 %
#5650
1"
b1100111 %
#5700
0"
b1101000 %
#5750
1"
b1101001 %
#5800
0"
b1101010 %
#5850
1"
b1101011 %
#5900
0"
b1101100 %
#5950
1"
b1101101 %
#6000
0"
b1101110 %
#6050
1"
b1101111 %
#6100
0"
b1110000 %
#6150
1"
b1110001 %
#6200
0"
b1110010 %
